mediaviz/__init__.py
mediaviz/community_utils.py
mediaviz/draw.py
mediaviz/rotation.py
mediaviz/scaling.py
mediaviz/utils.py
mediaviz/viz_parser.py
mediaviz-0.1.2.dist-info/METADATA
mediaviz-0.1.2.dist-info/RECORD
mediaviz-0.1.2.dist-info/WHEEL
mediaviz-0.1.2.dist-info/top_level.txt
