Metadata-Version: 2.1
Name: mediaviz
Version: 0.1.2
Summary: Visualize Networks With Force Atlas 2 Layout
Home-page: https://github.com/Tahsin-Mayeesha/Mediaviz
Author: Tahsin Mayeesha
Author-email: tasmiah.tahsin@hotmail.com
License: MIT
Platform: UNKNOWN
Classifier: Development Status :: 5 - Production/Stable
Classifier: Intended Audience :: Science/Research
Classifier: Topic :: Scientific/Engineering :: Mathematics
Classifier: License :: OSI Approved :: GNU General Public License v3 (GPLv3)
Classifier: Programming Language :: Python :: 3
Classifier: Programming Language :: Python :: 3.3
Classifier: Programming Language :: Python :: 3.4
Classifier: Programming Language :: Python :: 3.5
Classifier: Programming Language :: Python :: 3.6
Requires-Dist: fa2l
Requires-Dist: networkx (<2.0.0)
Requires-Dist: numpy
Requires-Dist: matplotlib
Requires-Dist: python-louvain
Requires-Dist: adjustText
